wechaty_client/__init__.py
wechaty_client/base.py
wechaty_client/bot.py
wechaty_client/error.py
wechaty_client/event.py
wechaty_client/logging_config.py
wechaty_client/types.py
wechaty_client-0.1.0.dist-info/METADATA
wechaty_client-0.1.0.dist-info/WHEEL
wechaty_client-0.1.0.dist-info/top_level.txt
wechaty_client-0.1.0.dist-info/RECORD
