Metadata-Version: 2.1
Name: wechaty-client
Version: 0.1.0
Summary: An implementation of a Redis-based Wechaty client in Python.
Home-page: 
Author: agihubme
Author-email: agihubme@gmail.com
Classifier: Programming Language :: Python :: 3
Classifier: License :: OSI Approved :: MIT License
Classifier: Operating System :: OS Independent
Requires-Python: >=3.9
Requires-Dist: redis
